svg_writer.py
svg_writer-0.5.dist-info/LICENSE.txt
svg_writer-0.5.dist-info/METADATA
svg_writer-0.5.dist-info/WHEEL
svg_writer-0.5.dist-info/top_level.txt
svg_writer-0.5.dist-info/RECORD
