Metadata-Version: 2.1
Name: svg-writer
Version: 0.5
Summary: Write SVG files with Python.
Home-page: https://github.com/ShayHill/svg_writer
Author: Shay Hill
Author-email: shay_public@hotmail.com
License: UNKNOWN
Platform: UNKNOWN
Classifier: Programming Language :: Python :: 3
Classifier: License :: OSI Approved :: MIT License
Classifier: Operating System :: OS Independent
Requires-Python: >=3.4
Requires-Dist: lxml
